ckanext_dc_serve-1.0.8-py3.12-nspkg.pth
ckanext/dc_serve/.gitignore
ckanext/dc_serve/__init__.py
ckanext/dc_serve/_version.py
ckanext/dc_serve/cli.py
ckanext/dc_serve/helpers.py
ckanext/dc_serve/jobs.py
ckanext/dc_serve/plugin.py
ckanext/dc_serve/res_file_lock.py
ckanext/dc_serve/route_funcs.py
ckanext/dc_serve/serve.py
ckanext/dc_serve/templates/package/resource_read.html
ckanext/dc_serve/tests/__init__.py
ckanext/dc_serve/tests/requirements.txt
ckanext/dc_serve/tests/test_helpers.py
ckanext/dc_serve/tests/test_jobs.py
ckanext/dc_serve/tests/test_res_file_lock.py
ckanext/dc_serve/tests/test_route.py
ckanext/dc_serve/tests/test_serve.py
ckanext/dc_serve/tests/data/calibration_beads_47.rtdc
ckanext/dc_serve/tests/data/cytoshot_blood.rtdc
ckanext_dc_serve-1.0.8.dist-info/licenses/LICENSE
ckanext_dc_serve-1.0.8.dist-info/METADATA
ckanext_dc_serve-1.0.8.dist-info/WHEEL
ckanext_dc_serve-1.0.8.dist-info/entry_points.txt
ckanext_dc_serve-1.0.8.dist-info/namespace_packages.txt
ckanext_dc_serve-1.0.8.dist-info/top_level.txt
ckanext_dc_serve-1.0.8.dist-info/RECORD
