Metadata-Version: 2.4
Name: ckanext-dc_serve
Version: 1.0.8
Summary: Serve DC on DCOR data via the CKAN API interface
Author: Paul Müller
Maintainer-email: Paul Müller <dev@craban.de>
License: GNU Affero General Public License v3 or later (AGPLv3+)
Project-URL: source, https://github.com/DCOR-dev/ckanext-dc_serve
Project-URL: tracker, https://github.com/DCOR-dev/ckanext-dc_serve/issues
Project-URL: changelog, https://github.com/DCOR-dev/ckanext-dc_serve/blob/main/CHANGELOG
Keywords: DC,DCOR,deformability,cytometry
Classifier: Operating System :: OS Independent
Classifier: Programming Language :: Python :: 3
Classifier: Topic :: Scientific/Engineering :: Visualization
Classifier: Intended Audience :: Science/Research
Requires-Python: <4,>=3.8
License-File: LICENSE
Requires-Dist: ckan<3,>=2.10.4
Requires-Dist: dclab>=0.66.0
Requires-Dist: dcor_shared>=1.0.3
Dynamic: license-file
